cookies_samesite_compat/__init__.py
cookies_samesite_compat/cookies.py
cookies_samesite_compat/middleware.py
cookies_samesite_compat-0.0.1.dist-info/LICENSE
cookies_samesite_compat-0.0.1.dist-info/METADATA
cookies_samesite_compat-0.0.1.dist-info/WHEEL
cookies_samesite_compat-0.0.1.dist-info/top_level.txt
cookies_samesite_compat-0.0.1.dist-info/RECORD
